[{"Party":"Australian Christians","Australian Christians":"0.0","Australian Fishing and Lifestyle Party":"8.0","Animal Justice":"19.0","Labor":"5.0","Motoring Enthusiast":"15.0","Sex Party":"30.0","Building Australia":"12.0","Mutual Party":"11.0","Coalition":"4.0","Democrats":"20.0","Democratic Labour":"1.0","Family First Party":"3.0","Greens":"28.0","Help End Marijuana Prohibition":"26.0","Katter's Australian":"10.0","Liberal Democrats":"24.0","Outdoor Recreation":"17.0","Pirate Party":"18.0","Palmer United Party":"14.0","Republican":"16.0","Rise Up Australia Party":"2.0","Socialist Alliance":"25.0","Shooters and Fishers":"9.0","Smokers Rights":"21.0","Secular Party of Australia":"23.0","#Sustainable Population Party":"27.0","Sports Party":"13.0","Freedom and Prosperity Party":"6.0","Australian Voice":"7.0","Voluntary Euthanasia Party":"29.0","The Wikileaks Party":"22.0"},{"Party":"Australian Fishing and Lifestyle Party","Australian Christians":"8.0","Australian Fishing and Lifestyle Party":"0.0","Animal Justice":"16.0","Labor":"20.0","Motoring Enthusiast":"7.0","Sex Party":"29.0","Building Australia":"4.0","Mutual Party":"10.0","Coalition":"14.0","Democrats":"9.0","Democratic Labour":"3.0","Family First Party":"12.0","Greens":"21.0","Help End Marijuana Prohibition":"19.0","Katter's Australian":"18.0","Liberal Democrats":"26.0","Outdoor Recreation":"27.0","Pirate Party":"24.0","Palmer United Party":"15.0","Republican":"11.0","Rise Up Australia Party":"13.0","Socialist Alliance":"17.0","Shooters and Fishers":"2.0","Smokers Rights":"28.0","Secular Party of Australia":"22.0","#Sustainable Population Party":"5.0","Sports Party":"6.0","Freedom and Prosperity Party":"1.0","Australian Voice":"23.0","Voluntary Euthanasia Party":"30.0","The Wikileaks Party":"25.0"},{"Party":"Animal Justice","Australian Christians":"21.0","Australian Fishing and Lifestyle Party":"29.0","Animal Justice":"0.0","Labor":"10.5","Motoring Enthusiast":"28.0","Sex Party":"7.0","Building Australia":"17.0","Mutual Party":"8.0","Coalition":"14.0","Democrats":"2.0","Democratic Labour":"22.0","Family First Party":"18.0","Greens":"10.5","Help End Marijuana Prohibition":"4.0","Katter's Australian":"13.0","Liberal Democrats":"23.0","Outdoor Recreation":"24.0","Pirate Party":"5.0","Palmer United Party":"12.0","Republican":"15.0","Rise Up Australia Party":"26.0","Socialist Alliance":"16.0","Shooters and Fishers":"30.0","Smokers Rights":"25.0","Secular Party of Australia":"9.0","#Sustainable Population Party":"1.0","Sports Party":"27.0","Freedom and Prosperity Party":"20.0","Australian Voice":"19.0","Voluntary Euthanasia Party":"3.0","The Wikileaks Party":"6.0"},{"Party":"Labor","Australian Christians":"16.0","Australian Fishing and Lifestyle Party":"25.0","Animal Justice":"2.0","Labor":"0.0","Motoring Enthusiast":"21.0","Sex Party":"3.0","Building Australia":"23.0","Mutual Party":"19.0","Coalition":"29.0","Democrats":"7.0","Democratic Labour":"14.0","Family First Party":"17.0","Greens":"6.0","Help End Marijuana Prohibition":"5.0","Katter's Australian":"13.0","Liberal Democrats":"11.0","Outdoor Recreation":"27.0","Pirate Party":"8.0","Palmer United Party":"12.0","Republican":"26.0","Rise Up Australia Party":"30.0","Socialist Alliance":"10.0","Shooters and Fishers":"15.0","Smokers Rights":"28.0","Secular Party of Australia":"1.0","#Sustainable Population Party":"20.0","Sports Party":"22.0","Freedom and Prosperity Party":"18.0","Australian Voice":"24.0","Voluntary Euthanasia Party":"4.0","The Wikileaks Party":"9.0"},{"Party":"Motoring Enthusiast","Australian Christians":"25.0","Australian Fishing and Lifestyle Party":"8.0","Animal Justice":"22.0","Labor":"27.0","Motoring Enthusiast":"0.0","Sex Party":"17.0","Building Australia":"10.0","Mutual Party":"9.0","Coalition":"26.0","Democrats":"15.0","Democratic Labour":"20.0","Family First Party":"18.0","Greens":"28.0","Help End Marijuana Prohibition":"7.0","Katter's Australian":"21.0","Liberal Democrats":"23.0","Outdoor Recreation":"11.0","Pirate Party":"14.0","Palmer United Party":"6.0","Republican":"16.0","Rise Up Australia Party":"19.0","Socialist Alliance":"30.0","Shooters and Fishers":"1.0","Smokers Rights":"24.0","Secular Party of Australia":"29.0","#Sustainable Population Party":"4.0","Sports Party":"5.0","Freedom and Prosperity Party":"2.0","Australian Voice":"3.0","Voluntary Euthanasia Party":"12.0","The Wikileaks Party":"13.0"},{"Party":"Sex Party","Australian Christians":"30.0","Australian Fishing and Lifestyle Party":"18.0","Animal Justice":"3.0","Labor":"4.0","Motoring Enthusiast":"19.0","Sex Party":"0.0","Building Australia":"16.0","Mutual Party":"12.0","Coalition":"21.0","Democrats":"6.0","Democratic Labour":"27.0","Family First Party":"28.0","Greens":"9.0","Help End Marijuana Prohibition":"5.0","Katter's Australian":"22.0","Liberal Democrats":"25.0","Outdoor Recreation":"26.0","Pirate Party":"8.0","Palmer United Party":"20.0","Republican":"24.0","Rise Up Australia Party":"29.0","Socialist Alliance":"10.0","Shooters and Fishers":"17.0","Smokers Rights":"23.0","Secular Party of Australia":"1.0","#Sustainable Population Party":"14.0","Sports Party":"11.0","Freedom and Prosperity Party":"13.0","Australian Voice":"15.0","Voluntary Euthanasia Party":"7.0","The Wikileaks Party":"2.0"},{"Party":"Building Australia","Australian Christians":"13.0","Australian Fishing and Lifestyle Party":"8.0","Animal Justice":"16.0","Labor":"24.0","Motoring Enthusiast":"9.0","Sex Party":"23.0","Building Australia":"0.0","Mutual Party":"2.0","Coalition":"21.0","Democrats":"6.0","Democratic Labour":"11.0","Family First Party":"12.0","Greens":"30.0","Help End Marijuana Prohibition":"10.0","Katter's Australian":"14.0","Liberal Democrats":"18.0","Outdoor Recreation":"28.0","Pirate Party":"25.0","Palmer United Party":"17.0","Republican":"19.0","Rise Up Australia Party":"15.0","Socialist Alliance":"27.0","Shooters and Fishers":"7.0","Smokers Rights":"20.0","Secular Party of Australia":"26.0","#Sustainable Population Party":"3.0","Sports Party":"5.0","Freedom and Prosperity Party":"4.0","Australian Voice":"1.0","Voluntary Euthanasia Party":"29.0","The Wikileaks Party":"22.0"},{"Party":"Mutual Party","Australian Christians":"20.0","Australian Fishing and Lifestyle Party":"16.0","Animal Justice":"24.0","Labor":"29.0","Motoring Enthusiast":"18.0","Sex Party":"21.0","Building Australia":"4.0","Mutual Party":"0.0","Coalition":"27.0","Democrats":"5.0","Democratic Labour":"12.0","Family First Party":"22.0","Greens":"30.0","Help End Marijuana Prohibition":"13.0","Katter's Australian":"6.0","Liberal Democrats":"10.0","Outdoor Recreation":"23.0","Pirate Party":"26.0","Palmer United Party":"17.0","Republican":"9.0","Rise Up Australia Party":"8.0","Socialist Alliance":"28.0","Shooters and Fishers":"11.0","Smokers Rights":"19.0","Secular Party of Australia":"25.0","#Sustainable Population Party":"1.0","Sports Party":"7.0","Freedom and Prosperity Party":"2.0","Australian Voice":"3.0","Voluntary Euthanasia Party":"14.0","The Wikileaks Party":"15.0"},{"Party":"Coalition","Australian Christians":"3.0","Australian Fishing and Lifestyle Party":"2.0","Animal Justice":"23.0","Labor":"18.0","Motoring Enthusiast":"8.0","Sex Party":"22.0","Building Australia":"6.0","Mutual Party":"13.0","Coalition":"0.0","Democrats":"14.0","Democratic Labour":"1.0","Family First Party":"4.0","Greens":"19.0","Help End Marijuana Prohibition":"30.0","Katter's Australian":"11.0","Liberal Democrats":"5.0","Outdoor Recreation":"9.0","Pirate Party":"24.0","Palmer United Party":"15.0","Republican":"12.0","Rise Up Australia Party":"21.0","Socialist Alliance":"29.0","Shooters and Fishers":"10.0","Smokers Rights":"26.0","Secular Party of Australia":"16.0","#Sustainable Population Party":"20.0","Sports Party":"7.0","Freedom and Prosperity Party":"28.0","Australian Voice":"27.0","Voluntary Euthanasia Party":"25.0","The Wikileaks Party":"17.0"},{"Party":"Democrats","Australian Christians":"24.0","Australian Fishing and Lifestyle Party":"18.0","Animal Justice":"2.0","Labor":"21.5","Motoring Enthusiast":"20.0","Sex Party":"6.0","Building Australia":"12.0","Mutual Party":"5.0","Coalition":"21.5","Democrats":"0.0","Democratic Labour":"26.0","Family First Party":"23.0","Greens":"16.0","Help End Marijuana Prohibition":"3.0","Katter's Australian":"14.0","Liberal Democrats":"30.0","Outdoor Recreation":"29.0","Pirate Party":"9.0","Palmer United Party":"15.0","Republican":"27.0","Rise Up Australia Party":"25.0","Socialist Alliance":"10.0","Shooters and Fishers":"17.0","Smokers Rights":"28.0","Secular Party of Australia":"8.0","#Sustainable Population Party":"1.0","Sports Party":"19.0","Freedom and Prosperity Party":"11.0","Australian Voice":"13.0","Voluntary Euthanasia Party":"7.0","The Wikileaks Party":"4.0"},{"Party":"Democratic Labour","Australian Christians":"2.0","Australian Fishing and Lifestyle Party":"6.0","Animal Justice":"23.0","Labor":"19.0","Motoring Enthusiast":"10.0","Sex Party":"29.0","Building Australia":"7.0","Mutual Party":"5.0","Coalition":"16.0","Democrats":"20.0","Democratic Labour":"0.0","Family First Party":"3.0","Greens":"30.0","Help End Marijuana Prohibition":"26.0","Katter's Australian":"4.0","Liberal Democrats":"15.0","Outdoor Recreation":"14.0","Pirate Party":"25.0","Palmer United Party":"18.0","Republican":"12.0","Rise Up Australia Party":"1.0","Socialist Alliance":"24.0","Shooters and Fishers":"17.0","Smokers Rights":"13.0","Secular Party of Australia":"21.0","#Sustainable Population Party":"22.0","Sports Party":"11.0","Freedom and Prosperity Party":"9.0","Australian Voice":"8.0","Voluntary Euthanasia Party":"28.0","The Wikileaks Party":"27.0"},{"Party":"Family First Party","Australian Christians":"4.0","Australian Fishing and Lifestyle Party":"5.0","Animal Justice":"16.0","Labor":"22.0","Motoring Enthusiast":"11.0","Sex Party":"30.0","Building Australia":"6.0","Mutual Party":"15.0","Coalition":"10.0","Democrats":"18.0","Democratic Labour":"2.0","Family First Party":"0.0","Greens":"23.0","Help End Marijuana Prohibition":"27.0","Katter's Australian":"13.0","Liberal Democrats":"9.0","Outdoor Recreation":"14.0","Pirate Party":"25.0","Palmer United Party":"1.0","Republican":"20.0","Rise Up Australia Party":"3.0","Socialist Alliance":"29.0","Shooters and Fishers":"12.0","Smokers Rights":"21.0","Secular Party of Australia":"28.0","#Sustainable Population Party":"19.0","Sports Party":"7.0","Freedom and Prosperity Party":"8.0","Australian Voice":"17.0","Voluntary Euthanasia Party":"24.0","The Wikileaks Party":"26.0"},{"Party":"Greens","Australian Christians":"24.0","Australian Fishing and Lifestyle Party":"27.0","Animal Justice":"6.0","Labor":"4.0","Motoring Enthusiast":"17.0","Sex Party":"5.0","Building Australia":"15.0","Mutual Party":"21.0","Coalition":"23.0","Democrats":"9.0","Democratic Labour":"16.0","Family First Party":"18.0","Greens":"0.0","Help End Marijuana Prohibition":"10.0","Katter's Australian":"19.0","Liberal Democrats":"29.0","Outdoor Recreation":"28.0","Pirate Party":"2.0","Palmer United Party":"20.0","Republican":"13.0","Rise Up Australia Party":"30.0","Socialist Alliance":"3.0","Shooters and Fishers":"25.0","Smokers Rights":"26.0","Secular Party of Australia":"8.0","#Sustainable Population Party":"11.0","Sports Party":"12.0","Freedom and Prosperity Party":"22.0","Australian Voice":"14.0","Voluntary Euthanasia Party":"7.0","The Wikileaks Party":"1.0"},{"Party":"Help End Marijuana Prohibition","Australian Christians":"30.0","Australian Fishing and Lifestyle Party":"12.0","Animal Justice":"4.0","Labor":"19.0","Motoring Enthusiast":"11.0","Sex Party":"15.0","Building Australia":"13.0","Mutual Party":"8.0","Coalition":"28.0","Democrats":"2.0","Democratic Labour":"26.0","Family First Party":"29.0","Greens":"23.0","Help End Marijuana Prohibition":"0.0","Katter's Australian":"5.0","Liberal Democrats":"21.0","Outdoor Recreation":"25.0","Pirate Party":"18.0","Palmer United Party":"20.0","Republican":"16.0","Rise Up Australia Party":"27.0","Socialist Alliance":"22.0","Shooters and Fishers":"14.0","Smokers Rights":"24.0","Secular Party of Australia":"17.0","#Sustainable Population Party":"7.0","Sports Party":"10.0","Freedom and Prosperity Party":"9.0","Australian Voice":"6.0","Voluntary Euthanasia Party":"3.0","The Wikileaks Party":"1.0"},{"Party":"Katter's Australian","Australian Christians":"6.0","Australian Fishing and Lifestyle Party":"13.0","Animal Justice":"24.0","Labor":"16.0","Motoring Enthusiast":"21.0","Sex Party":"29.0","Building Australia":"9.0","Mutual Party":"1.0","Coalition":"15.0","Democrats":"5.0","Democratic Labour":"3.0","Family First Party":"14.0","Greens":"28.0","Help End Marijuana Prohibition":"7.0","Katter's Australian":"0.0","Liberal Democrats":"4.0","Outdoor Recreation":"10.0","Pirate Party":"18.0","Palmer United Party":"11.0","Republican":"17.0","Rise Up Australia Party":"12.0","Socialist Alliance":"25.0","Shooters and Fishers":"8.0","Smokers Rights":"30.0","Secular Party of Australia":"26.0","#Sustainable Population Party":"19.0","Sports Party":"20.0","Freedom and Prosperity Party":"27.0","Australian Voice":"2.0","Voluntary Euthanasia Party":"22.0","The Wikileaks Party":"23.0"},{"Party":"Liberal Democrats","Australian Christians":"26.0","Australian Fishing and Lifestyle Party":"18.0","Animal Justice":"29.0","Labor":"24.0","Motoring Enthusiast":"17.0","Sex Party":"21.0","Building Australia":"10.0","Mutual Party":"5.0","Coalition":"22.0","Democrats":"3.0","Democratic Labour":"8.0","Family First Party":"15.0","Greens":"28.0","Help End Marijuana Prohibition":"9.0","Katter's Australian":"7.0","Liberal Democrats":"0.0","Outdoor Recreation":"1.0","Pirate Party":"19.0","Palmer United Party":"25.0","Republican":"6.0","Rise Up Australia Party":"27.0","Socialist Alliance":"30.0","Shooters and Fishers":"23.0","Smokers Rights":"2.0","Secular Party of Australia":"20.0","#Sustainable Population Party":"14.0","Sports Party":"11.0","Freedom and Prosperity Party":"12.0","Australian Voice":"13.0","Voluntary Euthanasia Party":"16.0","The Wikileaks Party":"4.0"},{"Party":"Outdoor Recreation","Australian Christians":"26.0","Australian Fishing and Lifestyle Party":"18.0","Animal Justice":"28.0","Labor":"24.0","Motoring Enthusiast":"17.0","Sex Party":"21.0","Building Australia":"10.0","Mutual Party":"5.0","Coalition":"22.0","Democrats":"3.0","Democratic Labour":"8.0","Family First Party":"15.0","Greens":"30.0","Help End Marijuana Prohibition":"9.0","Katter's Australian":"7.0","Liberal Democrats":"1.0","Outdoor Recreation":"0.0","Pirate Party":"19.0","Palmer United Party":"25.0","Republican":"6.0","Rise Up Australia Party":"27.0","Socialist Alliance":"29.0","Shooters and Fishers":"23.0","Smokers Rights":"2.0","Secular Party of Australia":"20.0","#Sustainable Population Party":"14.0","Sports Party":"11.0","Freedom and Prosperity Party":"12.0","Australian Voice":"13.0","Voluntary Euthanasia Party":"16.0","The Wikileaks Party":"4.0"},{"Party":"Pirate Party","Australian Christians":"28.0","Australian Fishing and Lifestyle Party":"20.0","Animal Justice":"10.0","Labor":"16.0","Motoring Enthusiast":"19.0","Sex Party":"6.0","Building Australia":"13.0","Mutual Party":"12.0","Coalition":"21.0","Democrats":"8.0","Democratic Labour":"18.0","Family First Party":"29.0","Greens":"1.0","Help End Marijuana Prohibition":"9.0","Katter's Australian":"23.0","Liberal Democrats":"7.0","Outdoor Recreation":"25.0","Pirate Party":"0.0","Palmer United Party":"24.0","Republican":"17.0","Rise Up Australia Party":"30.0","Socialist Alliance":"14.0","Shooters and Fishers":"22.0","Smokers Rights":"26.0","Secular Party of Australia":"2.0","#Sustainable Population Party":"11.0","Sports Party":"5.0","Freedom and Prosperity Party":"27.0","Australian Voice":"15.0","Voluntary Euthanasia Party":"3.0","The Wikileaks Party":"4.0"},{"Party":"Palmer United Party","Australian Christians":"14.0","Australian Fishing and Lifestyle Party":"4.0","Animal Justice":"22.0","Labor":"16.0","Motoring Enthusiast":"3.0","Sex Party":"28.0","Building Australia":"9.0","Mutual Party":"12.0","Coalition":"13.0","Democrats":"7.0","Democratic Labour":"21.0","Family First Party":"2.0","Greens":"19.0","Help End Marijuana Prohibition":"6.0","Katter's Australian":"10.0","Liberal Democrats":"30.0","Outdoor Recreation":"18.0","Pirate Party":"17.0","Palmer United Party":"0.0","Republican":"24.0","Rise Up Australia Party":"15.0","Socialist Alliance":"27.0","Shooters and Fishers":"5.0","Smokers Rights":"26.0","Secular Party of Australia":"20.0","#Sustainable Population Party":"23.0","Sports Party":"1.0","Freedom and Prosperity Party":"11.0","Australian Voice":"8.0","Voluntary Euthanasia Party":"29.0","The Wikileaks Party":"25.0"},{"Party":"Republican","Australian Christians":"27.0","Australian Fishing and Lifestyle Party":"16.0","Animal Justice":"11.0","Labor":"21.0","Motoring Enthusiast":"20.0","Sex Party":"4.0","Building Australia":"14.0","Mutual Party":"12.0","Coalition":"17.0","Democrats":"10.0","Democratic Labour":"29.0","Family First Party":"28.0","Greens":"18.0","Help End Marijuana Prohibition":"6.0","Katter's Australian":"22.0","Liberal Democrats":"1.0","Outdoor Recreation":"8.0","Pirate Party":"24.0","Palmer United Party":"30.0","Republican":"0.0","Rise Up Australia Party":"25.0","Socialist Alliance":"23.0","Shooters and Fishers":"9.0","Smokers Rights":"13.0","Secular Party of Australia":"3.0","#Sustainable Population Party":"2.0","Sports Party":"19.0","Freedom and Prosperity Party":"5.0","Australian Voice":"15.0","Voluntary Euthanasia Party":"7.0","The Wikileaks Party":"26.0"},{"Party":"Rise Up Australia Party","Australian Christians":"2.0","Australian Fishing and Lifestyle Party":"9.0","Animal Justice":"19.0","Labor":"17.0","Motoring Enthusiast":"14.0","Sex Party":"29.0","Building Australia":"7.0","Mutual Party":"4.0","Coalition":"11.0","Democrats":"21.0","Democratic Labour":"1.0","Family First Party":"3.0","Greens":"30.0","Help End Marijuana Prohibition":"27.0","Katter's Australian":"5.0","Liberal Democrats":"20.0","Outdoor Recreation":"12.0","Pirate Party":"22.0","Palmer United Party":"15.0","Republican":"23.0","Rise Up Australia Party":"0.0","Socialist Alliance":"26.0","Shooters and Fishers":"13.0","Smokers Rights":"16.0","Secular Party of Australia":"25.0","#Sustainable Population Party":"24.0","Sports Party":"10.0","Freedom and Prosperity Party":"6.0","Australian Voice":"8.0","Voluntary Euthanasia Party":"28.0","The Wikileaks Party":"18.0"},{"Party":"Socialist Alliance","Australian Christians":"26.0","Australian Fishing and Lifestyle Party":"24.0","Animal Justice":"6.0","Labor":"8.0","Motoring Enthusiast":"19.0","Sex Party":"7.0","Building Australia":"22.0","Mutual Party":"13.0","Coalition":"15.0","Democrats":"9.0","Democratic Labour":"14.0","Family First Party":"27.0","Greens":"1.0","Help End Marijuana Prohibition":"3.0","Katter's Australian":"17.0","Liberal Democrats":"21.0","Outdoor Recreation":"30.0","Pirate Party":"2.0","Palmer United Party":"18.0","Republican":"16.0","Rise Up Australia Party":"28.0","Socialist Alliance":"0.0","Shooters and Fishers":"25.0","Smokers Rights":"23.0","Secular Party of Australia":"12.0","#Sustainable Population Party":"10.0","Sports Party":"11.0","Freedom and Prosperity Party":"29.0","Australian Voice":"20.0","Voluntary Euthanasia Party":"4.0","The Wikileaks Party":"5.0"},{"Party":"Shooters and Fishers","Australian Christians":"21.0","Australian Fishing and Lifestyle Party":"7.0","Animal Justice":"29.0","Labor":"20.0","Motoring Enthusiast":"6.0","Sex Party":"23.0","Building Australia":"4.0","Mutual Party":"5.0","Coalition":"19.0","Democrats":"8.0","Democratic Labour":"22.0","Family First Party":"15.0","Greens":"30.0","Help End Marijuana Prohibition":"9.0","Katter's Australian":"12.0","Liberal Democrats":"18.0","Outdoor Recreation":"16.0","Pirate Party":"26.0","Palmer United Party":"14.0","Republican":"11.0","Rise Up Australia Party":"13.0","Socialist Alliance":"28.0","Shooters and Fishers":"0.0","Smokers Rights":"17.0","Secular Party of Australia":"25.0","#Sustainable Population Party":"10.0","Sports Party":"3.0","Freedom and Prosperity Party":"2.0","Australian Voice":"1.0","Voluntary Euthanasia Party":"24.0","The Wikileaks Party":"27.0"},{"Party":"Smokers Rights","Australian Christians":"26.0","Australian Fishing and Lifestyle Party":"18.0","Animal Justice":"29.0","Labor":"24.0","Motoring Enthusiast":"17.0","Sex Party":"21.0","Building Australia":"10.0","Mutual Party":"5.0","Coalition":"22.0","Democrats":"3.0","Democratic Labour":"8.0","Family First Party":"15.0","Greens":"28.0","Help End Marijuana Prohibition":"9.0","Katter's Australian":"7.0","Liberal Democrats":"1.0","Outdoor Recreation":"2.0","Pirate Party":"19.0","Palmer United Party":"25.0","Republican":"6.0","Rise Up Australia Party":"27.0","Socialist Alliance":"30.0","Shooters and Fishers":"23.0","Smokers Rights":"0.0","Secular Party of Australia":"20.0","#Sustainable Population Party":"14.0","Sports Party":"11.0","Freedom and Prosperity Party":"12.0","Australian Voice":"13.0","Voluntary Euthanasia Party":"16.0","The Wikileaks Party":"4.0"},{"Party":"Secular Party of Australia","Australian Christians":"30.0","Australian Fishing and Lifestyle Party":"21.0","Animal Justice":"10.0","Labor":"11.0","Motoring Enthusiast":"23.0","Sex Party":"3.0","Building Australia":"15.0","Mutual Party":"17.0","Coalition":"14.0","Democrats":"1.0","Democratic Labour":"28.0","Family First Party":"29.0","Greens":"7.0","Help End Marijuana Prohibition":"9.0","Katter's Australian":"19.0","Liberal Democrats":"8.0","Outdoor Recreation":"18.0","Pirate Party":"5.0","Palmer United Party":"16.0","Republican":"6.0","Rise Up Australia Party":"27.0","Socialist Alliance":"12.0","Shooters and Fishers":"25.0","Smokers Rights":"24.0","Secular Party of Australia":"0.0","#Sustainable Population Party":"13.0","Sports Party":"20.0","Freedom and Prosperity Party":"26.0","Australian Voice":"22.0","Voluntary Euthanasia Party":"2.0","The Wikileaks Party":"4.0"},{"Party":"#Sustainable Population Party","Australian Christians":"22.0","Australian Fishing and Lifestyle Party":"14.0","Animal Justice":"8.0","Labor":"15.666666666666666","Motoring Enthusiast":"4.0","Sex Party":"12.0","Building Australia":"3.0","Mutual Party":"1.0","Coalition":"11.0","Democrats":"5.0","Democratic Labour":"25.0","Family First Party":"21.0","Greens":"15.333333333333334","Help End Marijuana Prohibition":"9.0","Katter's Australian":"23.0","Liberal Democrats":"13.0","Outdoor Recreation":"30.0","Pirate Party":"20.0","Palmer United Party":"19.0","Republican":"17.0","Rise Up Australia Party":"27.0","Socialist Alliance":"28.0","Shooters and Fishers":"26.0","Smokers Rights":"29.0","Secular Party of Australia":"18.0","#Sustainable Population Party":"0.0","Sports Party":"6.0","Freedom and Prosperity Party":"24.0","Australian Voice":"2.0","Voluntary Euthanasia Party":"10.0","The Wikileaks Party":"7.0"},{"Party":"Sports Party","Australian Christians":"14.0","Australian Fishing and Lifestyle Party":"4.0","Animal Justice":"26.0","Labor":"28.0","Motoring Enthusiast":"6.0","Sex Party":"17.0","Building Australia":"7.0","Mutual Party":"5.0","Coalition":"21.0","Democrats":"16.0","Democratic Labour":"13.0","Family First Party":"15.0","Greens":"27.0","Help End Marijuana Prohibition":"22.0","Katter's Australian":"23.0","Liberal Democrats":"18.0","Outdoor Recreation":"29.0","Pirate Party":"25.0","Palmer United Party":"19.0","Republican":"9.0","Rise Up Australia Party":"12.0","Socialist Alliance":"24.0","Shooters and Fishers":"11.0","Smokers Rights":"30.0","Secular Party of Australia":"20.0","#Sustainable Population Party":"2.0","Sports Party":"0.0","Freedom and Prosperity Party":"1.0","Australian Voice":"3.0","Voluntary Euthanasia Party":"8.0","The Wikileaks Party":"10.0"},{"Party":"Freedom and Prosperity Party","Australian Christians":"12.0","Australian Fishing and Lifestyle Party":"10.0","Animal Justice":"26.0","Labor":"22.0","Motoring Enthusiast":"11.0","Sex Party":"23.0","Building Australia":"3.0","Mutual Party":"2.0","Coalition":"21.0","Democrats":"13.0","Democratic Labour":"8.0","Family First Party":"9.0","Greens":"30.0","Help End Marijuana Prohibition":"14.0","Katter's Australian":"6.0","Liberal Democrats":"15.0","Outdoor Recreation":"18.0","Pirate Party":"20.0","Palmer United Party":"17.0","Republican":"16.0","Rise Up Australia Party":"5.0","Socialist Alliance":"28.0","Shooters and Fishers":"7.0","Smokers Rights":"19.0","Secular Party of Australia":"29.0","#Sustainable Population Party":"24.0","Sports Party":"4.0","Freedom and Prosperity Party":"0.0","Australian Voice":"1.0","Voluntary Euthanasia Party":"27.0","The Wikileaks Party":"25.0"},{"Party":"Australian Voice","Australian Christians":"8.0","Australian Fishing and Lifestyle Party":"6.0","Animal Justice":"17.0","Labor":"29.0","Motoring Enthusiast":"4.0","Sex Party":"18.0","Building Australia":"3.0","Mutual Party":"11.0","Coalition":"19.0","Democrats":"15.0","Democratic Labour":"13.0","Family First Party":"20.0","Greens":"30.0","Help End Marijuana Prohibition":"9.0","Katter's Australian":"12.0","Liberal Democrats":"28.0","Outdoor Recreation":"26.0","Pirate Party":"24.0","Palmer United Party":"7.0","Republican":"21.0","Rise Up Australia Party":"16.0","Socialist Alliance":"23.0","Shooters and Fishers":"5.0","Smokers Rights":"27.0","Secular Party of Australia":"22.0","#Sustainable Population Party":"2.0","Sports Party":"10.0","Freedom and Prosperity Party":"1.0","Australian Voice":"0.0","Voluntary Euthanasia Party":"25.0","The Wikileaks Party":"14.0"},{"Party":"Voluntary Euthanasia Party","Australian Christians":"27.0","Australian Fishing and Lifestyle Party":"18.0","Animal Justice":"28.0","Labor":"5.5","Motoring Enthusiast":"13.0","Sex Party":"3.0","Building Australia":"15.0","Mutual Party":"20.0","Coalition":"22.5","Democrats":"10.0","Democratic Labour":"26.5","Family First Party":"27.0","Greens":"5.5","Help End Marijuana Prohibition":"1.0","Katter's Australian":"26.5","Liberal Democrats":"7.0","Outdoor Recreation":"22.0","Pirate Party":"4.0","Palmer United Party":"17.0","Republican":"19.5","Rise Up Australia Party":"27.0","Socialist Alliance":"13.5","Shooters and Fishers":"19.0","Smokers Rights":"19.5","Secular Party of Australia":"2.0","#Sustainable Population Party":"9.0","Sports Party":"8.0","Freedom and Prosperity Party":"19.0","Australian Voice":"19.0","Voluntary Euthanasia Party":"0.0","The Wikileaks Party":"11.0"},{"Party":"The Wikileaks Party","Australian Christians":"27.0","Australian Fishing and Lifestyle Party":"26.0","Animal Justice":"4.0","Labor":"6.0","Motoring Enthusiast":"24.0","Sex Party":"3.0","Building Australia":"21.0","Mutual Party":"18.0","Coalition":"17.0","Democrats":"11.0","Democratic Labour":"12.0","Family First Party":"22.0","Greens":"1.0","Help End Marijuana Prohibition":"2.0","Katter's Australian":"14.0","Liberal Democrats":"19.0","Outdoor Recreation":"28.0","Pirate Party":"8.0","Palmer United Party":"16.0","Republican":"15.0","Rise Up Australia Party":"30.0","Socialist Alliance":"7.0","Shooters and Fishers":"29.0","Smokers Rights":"25.0","Secular Party of Australia":"13.0","#Sustainable Population Party":"10.0","Sports Party":"9.0","Freedom and Prosperity Party":"23.0","Australian Voice":"20.0","Voluntary Euthanasia Party":"5.0","The Wikileaks Party":"0.0"}]
